[{"title":"Intel core i9 9900k 3.6 ghz - barely used - receipt","description":"Intel core i9 9900k 3.6 ghz Never overclocked Barely used Have receipt can deliver","date":"2022-03-15T04:29:04.000Z","image":"https://i.ebayimg.com/00/s/ODAwWDgwMA==/z/wKsAAOSwDg5iMBV-/$_57.JPG","images":["https://i.ebayimg.com/00/s/ODAwWDgwMA==/z/wKsAAOSwDg5iMBV-/$_57.JPG"],"attributes":{"forsaleby":"ownr","condition":"usedlikenew","price":350,"location":"731 Maple Avenue, Burlington, ON","type":"OFFERED"},"url":"https://www.kijiji.ca/v-other/mississauga-peel-region/intel-core-i9-9900k-3-6-ghz-barely-used-receipt/1608918030","id":"1608918030","metCriteria":{"tags":["CPU","Intel","i9","9xxx","High","Coffee Lake"],"Contains_AND":["i9"],"Contains_OR":["9820","9900","9920","9940","9960","9980","9990","Coffee Lake","9th gen","ninth gen","nineth gen"],"Contains_NOR":["Wanted","Want to buy","like to buy"],"MaxPrice":450,"filter":"short"},"fullDescription":"Intel core i9 9900k 3.6 ghz Never overclocked Barely used Have receipt can deliver"},{"title":"Intel i9-9900K CPU","description":"I am going through my older computer equipment and posting everything that I will not be using ...","date":"2022-03-25T01:09:10.000Z","image":"https://i.ebayimg.com/00/s/MTYwMFgxNDM4/z/VmUAAOSwLV5iPRYW/$_57.JPG","images":["https://i.ebayimg.com/00/s/MTYwMFgxNDM4/z/VmUAAOSwLV5iPRYW/$_57.JPG","https://i.ebayimg.com/00/s/MTYwMFgxMjAw/z/ltQAAOSwr5hiPRYX/$_57.JPG"],"attributes":{"forsaleby":"ownr","condition":"usedgood","price":320,"location":"Oakville, ON L6H","type":"OFFERED"},"url":"https://www.kijiji.ca/v-computer-components/oakville-halton-region/intel-i9-9900k-cpu/1610164034","id":"1610164034","metCriteria":{"tags":["CPU","Intel","i9","9xxx","High","Coffee Lake"],"Contains_AND":["i9"],"Contains_OR":["9820","9900","9920","9940","9960","9980","9990","Coffee Lake","9th gen","ninth gen","nineth gen"],"Contains_NOR":["Wanted","Want to buy","like to buy"],"MaxPrice":450,"filter":"short"},"fullDescription":"I am going through my older computer equipment and posting everything that I will not be using ..."},{"title":"Intel Core i9-9900 Desktop Processor 8 Cores up to 5.0GHz LGA115","description":"Intel Core i9-9900 Desktop Processor 8 Cores up to 5.0GHz LGA1151 300 Series 65W Brand new in box, ...","date":"2022-03-04T20:31:46.000Z","image":"https://i.ebayimg.com/00/s/ODAwWDYxOA==/z/DGgAAOSwEDZhfr3y/$_57.JPG","images":["https://i.ebayimg.com/00/s/ODAwWDYxOA==/z/DGgAAOSwEDZhfr3y/$_57.JPG","https://i.ebayimg.com/00/s/NDQ4WDgwMA==/z/GB4AAOSw~89hfr3u/$_57.JPG","https://i.ebayimg.com/00/s/NjE4WDgwMA==/z/SNwAAOSw4Cxhfr30/$_57.JPG","https://i.ebayimg.com/00/s/NzgyWDgwMA==/z/kioAAOSwV5Fhfr33/$_57.JPG","https://i.ebayimg.com/00/s/Nzk5WDgwMA==/z/RS4AAOSwI79hfr38/$_57.JPG","https://i.ebayimg.com/00/s/ODAwWDgwMA==/z/crIAAOSwq~phfr3~/$_57.JPG"],"attributes":{"forsaleby":"ownr","condition":"new","price":500,"location":"Brampton, ON L6P","type":"OFFERED"},"url":"https://www.kijiji.ca/v-computer-components/mississauga-peel-region/intel-core-i9-9900-desktop-processor-8-cores-up-to-5-0ghz-lga115/1592175468","id":"1592175468","metCriteria":{"tags":["CPU","Intel","i9","9xxx","High","Coffee Lake"],"Contains_AND":["i9"],"Contains_OR":["9820","9900","9920","9940","9960","9980","9990","Coffee Lake","9th gen","ninth gen","nineth gen"],"Contains_NOR":["Wanted","Want to buy","like to buy"],"MaxPrice":450,"filter":"short"},"fullDescription":"Intel Core i9-9900 Desktop Processor 8 Cores up to 5.0GHz LGA1151 300 Series 65W Brand new in box, ..."},{"title":"i7-8700K","description":"8700k in excellent condition. Can easily overclock to 5ghz.","date":"2022-02-27T20:25:58.000Z","image":"https://i.ebayimg.com/00/s/ODAwWDY4OQ==/z/dc4AAOSwcB1iG94X/$_57.JPG","images":["https://i.ebayimg.com/00/s/ODAwWDY4OQ==/z/dc4AAOSwcB1iG94X/$_57.JPG"],"attributes":{"forsaleby":"ownr","price":230,"location":"Mississauga, ON L5B 4C1","type":"OFFERED"},"url":"https://www.kijiji.ca/v-computer-components/mississauga-peel-region/i7-8700k/1607059400","id":"1607059400","metCriteria":{"tags":["CPU","Intel","i7","8xxx","high","Coffee Lake"],"Contains_AND":["i7"],"Contains_OR":["8700","8086","Coffee Lake","8th gen","eigth gen"],"Contains_NOR":["Wanted","Want to buy","like to buy","heat sink only","laptop cpu","notebook cpu"],"MaxPrice":250,"filter":"short"},"fullDescription":"8700k in excellent condition. Can easily overclock to 5ghz."},{"title":"Intel i7 8700K CPU","description":"In mint condition, Intel i7 8700K CPU - $250. Haven't used it since I bought it as I was busy with ...","date":"2022-03-11T03:01:09.000Z","image":"https://i.ebayimg.com/00/s/ODAwWDYwMA==/z/-wkAAOSw1yJiKrqe/$_57.JPG","images":["https://i.ebayimg.com/00/s/ODAwWDYwMA==/z/-wkAAOSw1yJiKrqe/$_57.JPG"],"attributes":{"forsaleby":"ownr","fulfillment":"delivery","condition":"usedlikenew","price":250,"location":"Mississauga, ON L5B","type":"OFFERED"},"url":"https://www.kijiji.ca/v-computer-components/mississauga-peel-region/intel-i7-8700k-cpu/1608408705","id":"1608408705","metCriteria":{"tags":["CPU","Intel","i7","8xxx","high","Coffee Lake"],"Contains_AND":["i7"],"Contains_OR":["8700","8086","Coffee Lake","8th gen","eigth gen"],"Contains_NOR":["Wanted","Want to buy","like to buy","heat sink only","laptop cpu","notebook cpu"],"MaxPrice":250,"filter":"short"},"fullDescription":"In mint condition, Intel i7 8700K CPU - $250. Haven't used it since I bought it as I was busy with ..."},{"title":"Intel core i7 9700k","description":"Intel core i7 9700k. Posted in computers, desktop computers in Mississauga / Peel Region. March 28, ...","date":"2022-03-28T14:14:14.000Z","image":"https://i.ebayimg.com/00/s/MzUwWDY3MA==/z/7ToAAOSwyPJiQcJp/$_57.JPG","images":["https://i.ebayimg.com/00/s/MzUwWDY3MA==/z/7ToAAOSwyPJiQcJp/$_57.JPG"],"attributes":{"desktopbrand":"desktopintel","forsaleby":"ownr","condition":"usedlikenew","price":280,"location":"Mississauga, ON L5V2H1","type":"OFFERED"},"url":"https://www.kijiji.ca/v-desktop-computers/mississauga-peel-region/intel-core-i7-9700k/1610619781","id":"1610619781","metCriteria":{"tags":["CPU","Intel","i7","9xxx","High","Coffee Lake"],"Contains_AND":["i7"],"Contains_OR":["9700","Coffee Lake","9th gen","ninth gen","nineth gen"],"Contains_NOR":["Wanted","Want to buy","like to buy","heat sink only","laptop cpu","notebook cpu"],"MaxPrice":350,"filter":"short"},"fullDescription":"Intel core i7 9700k. Posted in computers, desktop computers in Mississauga / Peel Region. March 28, ..."},{"title":"i5-8400 cpu ddr4 8gb 3000mhz ram","description":"150 for cpu 50 for ram 175 for both","date":"2022-04-01T01:15:41.000Z","image":"https://i.ebayimg.com/00/s/MTYwMFgxMjAw/z/eOsAAOSwVbhiRlHF/$_57.JPG","images":["https://i.ebayimg.com/00/s/MTYwMFgxMjAw/z/eOsAAOSwVbhiRlHF/$_57.JPG"],"attributes":{"forsaleby":"ownr","condition":"usedlikenew","price":150,"location":"Etobicoke, ON M9C0C3","type":"OFFERED"},"url":"https://www.kijiji.ca/v-computer-components/mississauga-peel-region/i5-8400-cpu-ddr4-8gb-3000mhz-ram/1611079041","id":"1611079041","metCriteria":{"tags":["CPU","Intel","i5","8xxx","High","Coffee Lake"],"Contains_AND":["i5"],"Contains_OR":["8400","8500","8600","Coffee Lake","8th gen","eigth gen"],"Contains_NOR":["Wanted","Want to buy","like to buy","heat sink only","laptop cpu","notebook cpu"],"MaxPrice":150,"filter":"short"},"fullDescription":"150 for cpu 50 for ram 175 for both"},{"title":"Intel Core i7-8700K 4.7GHz CPU LGA1151","description":"Perfect condition i7-8700K about 5 months old purchased brand new. Stock clock speed is 3.7Ghz with ...","date":"2022-02-09T19:50:28.000Z","image":"https://i.ebayimg.com/00/s/NDUwWDM4Nw==/z/fQAAAOSwzRRiBBnN/$_57.JPG","images":["https://i.ebayimg.com/00/s/NDUwWDM4Nw==/z/fQAAAOSwzRRiBBnN/$_57.JPG"],"attributes":{"desktopbrand":"desktopintel","fulfillment":"shippingdelivery","payment":"cashless","forsaleby":"ownr","condition":"usedlikenew","price":275,"location":"Toronto, ON M8Z3P2","type":"OFFERED"},"url":"https://www.kijiji.ca/v-desktop-computers/city-of-toronto/intel-core-i7-8700k-4-7ghz-cpu-lga1151/1604980703","id":"1604980703","metCriteria":{"tags":["CPU","Intel","i7","8xxx","high","Coffee Lake"],"Contains_AND":["i7"],"Contains_OR":["8700","8086","Coffee Lake","8th gen","eigth gen"],"Contains_NOR":["Wanted","Want to buy","like to buy","heat sink only","laptop cpu","notebook cpu"],"MaxPrice":250,"filter":"short"},"fullDescription":"Perfect condition i7-8700K about 5 months old purchased brand new. Stock clock speed is 3.7Ghz with ..."},{"title":"Broken Intel CPU 9th Gen Core i5 9400 2.9GHz AS IS","description":"Not functioning Selling for parts Physically perfect shape Killed in a power surge","date":"2022-03-30T22:21:01.000Z","image":"https://i.ebayimg.com/00/s/MTYwMFgxMjAw/z/YBoAAOSw-LhiRNci/$_57.JPG","images":["https://i.ebayimg.com/00/s/MTYwMFgxMjAw/z/YBoAAOSw-LhiRNci/$_57.JPG","https://i.ebayimg.com/00/s/MTYwMFgxMjAw/z/UHkAAOSwHRpiRNck/$_57.JPG","https://i.ebayimg.com/00/s/MTYwMFgxMjAw/z/qZ8AAOSwpB1iRNcm/$_57.JPG","https://i.ebayimg.com/00/s/MTYwMFgxMjAw/z/4iQAAOSwdMZiRNcn/$_57.JPG"],"attributes":{"forsaleby":"ownr","fulfillment":"deliverycurbsideshipping","payment":"cashless","price":40,"location":"Toronto, ON M6N","type":"OFFERED"},"url":"https://www.kijiji.ca/v-computer-components/city-of-toronto/broken-intel-cpu-9th-gen-core-i5-9400-2-9ghz-as-is/1610937639","id":"1610937639","metCriteria":{"tags":["CPU","Intel","i5","9xxx","High","Coffee Lake"],"Contains_AND":["i5"],"Contains_OR":["9400","9500","9600","Coffee Lake","9th gen","ninth gen","nineth gen"],"Contains_NOR":["Wanted","Want to buy","like to buy","heat sink only","laptop cpu","notebook cpu"],"MaxPrice":160,"filter":"short"},"fullDescription":"Not functioning Selling for parts Physically perfect shape Killed in a power surge"},{"title":"Intel i3-8100 CPU in mint condition ","description":"Selling an intel i3-8100 CPU in mint condition. Pick up is at Markham Road near Steeles.","date":"2022-03-21T23:09:12.000Z","image":"https://i.ebayimg.com/00/s/MTU1NVgxMDgw/z/cfYAAOSwtbFiOQUh/$_57.JPG","images":["https://i.ebayimg.com/00/s/MTU1NVgxMDgw/z/cfYAAOSwtbFiOQUh/$_57.JPG","https://i.ebayimg.com/00/s/MTU1NVgxMDgw/z/6vsAAOSwZgtiOQUk/$_57.JPG"],"attributes":{"forsaleby":"ownr","condition":"usedlikenew","price":100,"location":"Toronto, ON M1V5P7","type":"OFFERED"},"url":"https://www.kijiji.ca/v-computer-components/city-of-toronto/intel-i3-8100-cpu-in-mint-condition/1609777186","id":"1609777186","metCriteria":{"tags":["CPU","Intel","i3","8xxx","mid","Coffee Lake"],"Contains_AND":["i3"],"Contains_OR":["8100","8300","8350","Coffee Lake","8th gen","eigth gen"],"Contains_NOR":["Wanted","Want to buy","like to buy","heat sink only","laptop cpu","notebook cpu"],"MaxPrice":110,"filter":"short"},"fullDescription":"Selling an intel i3-8100 CPU in mint condition. Pick up is at Markham Road near Steeles."}]